payerurl/__init__.py
payerurl/client.py
payerurl/request.py
payerurl/utils.py
payerurl-0.1.0.dist-info/METADATA
payerurl-0.1.0.dist-info/WHEEL
payerurl-0.1.0.dist-info/top_level.txt
payerurl-0.1.0.dist-info/RECORD
