Metadata-Version: 2.4
Name: payerurl
Version: 0.1.0
Summary: Official Python SDK for PayerURL payment gateway
Author: Golam Kibria Papel
License: MIT
Requires-Dist: requests
